browser_history_analytics/__init__.py
browser_history_analytics/app.py
browser_history_analytics/graphs.py
browser_history_analytics/main.py
browser_history_analytics/utils.py
browser_history_analytics-0.1.5.dist-info/licenses/LICENSE
browser_history_analytics-0.1.5.dist-info/METADATA
browser_history_analytics-0.1.5.dist-info/WHEEL
browser_history_analytics-0.1.5.dist-info/entry_points.txt
browser_history_analytics-0.1.5.dist-info/top_level.txt
browser_history_analytics-0.1.5.dist-info/RECORD
