Metadata-Version: 2.4
Name: browser-history-analytics
Version: 0.1.5
Summary: A package to visualize your browser history :D
Author: Arpit Sengar (arpy8)
Classifier: Programming Language :: Python :: 3
Classifier: License :: OSI Approved :: MIT License
Classifier: Operating System :: OS Independent
Requires-Python: >=3.7
License-File: LICENSE
Requires-Dist: streamlit
Requires-Dist: plotly
Requires-Dist: pandas
Requires-Dist: browser-history
Requires-Dist: numpy
Requires-Dist: seaborn
Requires-Dist: matplotlib
Requires-Dist: urllib3
Requires-Dist: setuptools>=66.1.1
Requires-Dist: rich
Requires-Dist: requests
Dynamic: author
Dynamic: classifier
Dynamic: description
Dynamic: description-content-type
Dynamic: license-file
Dynamic: requires-dist
Dynamic: requires-python
Dynamic: summary
